.github/python-version.txt
.pre-commit-config.yaml
spamanalyzer/__init__.py
spamanalyzer/data_structures.py
spamanalyzer/date.py
spamanalyzer/domain.py
spamanalyzer/errors.py
spamanalyzer/ml/__classifier.py
spamanalyzer/ml/__init__.py
spamanalyzer/ml/classifier.pkl
spamanalyzer/plugins.py
spamanalyzer/py.typed
spamanalyzer/utils.py
spam_analyzer-1.0.11.dist-info/LICENSE
spam_analyzer-1.0.11.dist-info/METADATA
spam_analyzer-1.0.11.dist-info/WHEEL
spam_analyzer-1.0.11.dist-info/entry_points.txt
spam_analyzer-1.0.11.dist-info/RECORD
