Metadata-Version: 2.1
Name: spam-analyzer
Version: 1.0.11
Summary: A simple email analyzer
Home-page: http://docs.spamanalyzer.tech/
License: GPLv3
Keywords: spam,spam-analyzer,cybersecurity
Author: Matteo Spanio
Author-email: spanio@dei.unipd.it
Requires-Python: >=3.10,<4.0
Classifier: Development Status :: 3 - Alpha
Classifier: Intended Audience :: Developers
Classifier: License :: OSI Approved :: GNU General Public License v3 (GPLv3)
Classifier: License :: Other/Proprietary License
Classifier: Operating System :: OS Independent
Classifier: Programming Language :: Python :: 3
Classifier: Programming Language :: Python :: 3.10
Classifier: Programming Language :: Python :: 3.11
Classifier: Programming Language :: Python :: 3.12
Requires-Dist: PyYAML (>=6.0,<7.0)
Requires-Dist: beautifulsoup4 (>=4.12.2,<5.0.0)
Requires-Dist: click (>=8.1.6,<9.0.0)
Requires-Dist: click-extra (>=4.6.3,<5.0.0)
Requires-Dist: dnspython (>=2.4.0,<3.0.0)
Requires-Dist: mail-parser (>=3.15.0,<4.0.0)
Requires-Dist: nltk (>=3.8.1,<4.0.0)
Requires-Dist: numpy (>=1.25.1,<2.0.0)
Requires-Dist: pandas (>=2.0.3,<3.0.0)
Requires-Dist: requests (>=2.31.0,<3.0.0)
Requires-Dist: rich (>=13.4.2,<14.0.0)
Requires-Dist: scikit-learn (>=1.1.2,<2.0.0)
Requires-Dist: textblob (>=0.17.1,<0.18.0)
Project-URL: Repository, https://github.com/matteospanio/spam-analyzer
